jenkins_job_linter/__init__.py
jenkins_job_linter/config.py
jenkins_job_linter/jjb_subcommand.py
jenkins_job_linter/linters.py
jenkins_job_linter/models.py
jenkins_job_linter-0.12.0.dist-info/AUTHORS
jenkins_job_linter-0.12.0.dist-info/LICENSE
jenkins_job_linter-0.12.0.dist-info/METADATA
jenkins_job_linter-0.12.0.dist-info/WHEEL
jenkins_job_linter-0.12.0.dist-info/entry_points.txt
jenkins_job_linter-0.12.0.dist-info/pbr.json
jenkins_job_linter-0.12.0.dist-info/top_level.txt
jenkins_job_linter-0.12.0.dist-info/RECORD
