Metadata-Version: 2.1
Name: jenkins-job-linter
Version: 0.12.0
Summary: Perform linting checks against a directory of Jenkins job XML
Home-page: https://github.com/OddBloke/jenkins-job-linter
Author: Daniel Watkins
Author-email: daniel@daniel-watkins.co.uk
License: Apache-2
Keywords: jenkins,jenkins-job-builder
Classifier: Development Status :: 3 - Alpha
Classifier: Environment :: Console
Classifier: Intended Audience :: Developers
Classifier: Intended Audience :: Information Technology
Classifier: License :: OSI Approved :: Apache Software License
Classifier: Operating System :: OS Independent
Classifier: Programming Language :: Python
Classifier: Programming Language :: Python :: 3 :: Only
License-File: LICENSE
License-File: AUTHORS
Requires-Dist: click <8
Requires-Dist: stevedore
Requires-Dist: jenkins-job-builder >=2.0.0.0b1
Requires-Dist: python-jenkins >=0.4.15
